Workbook

Sheet Test Scenarios
A1: Scenario ID | B1: Priority | C1: Module | D1: PRD Ref | E1: Test Scenario | F1: Why It Ranks Here | G1: No. of Test Cases
A2: TS-01 | B2: Critical | C2: Checkout | D2: FR-12 | E2: Verify checkout accepts only valid recipient, phone, address and payment details, and blocks invalid input | F2: Last step before money changes hands; bad validation means bad or undeliverable orders | G2: =COUNTIF('Test Cases'!$B:$B,A2) -> 15
A3: TS-02 | B3: Critical | C3: Order Confirmation | D3: FR-13 | E3: Verify placing an order creates a unique order number, shows correct confirmation and resets cart and coupon | F3: Proves the purchase actually completed and state is clean afterwards | G3: =COUNTIF('Test Cases'!$B:$B,A3) -> 6
A4: TS-03 | B4: Critical | C4: Order Total | D4: FR-08 | E4: Verify total = subtotal + delivery - discount everywhere it is shown | F4: Wrong money amounts directly hurt customers and the business | G4: =COUNTIF('Test Cases'!$B:$B,A4) -> 6
A5: TS-04 | B5: Critical | C5: Cart | D5: FR-05 | E5: Verify items can be added, edited and removed, and quantity rules and stock limits are enforced | F5: Core purchase path; stock and quantity errors cause oversell and wrong totals | G5: =COUNTIF('Test Cases'!$B:$B,A5) -> 14
A6: TS-05 | B6: High | C6: Coupons | D6: FR-06 | E6: Verify valid coupons apply the correct discount, invalid ones are rejected and discounts never stack | F6: Discount logic is a common source of revenue loss | G6: =COUNTIF('Test Cases'!$B:$B,A6) -> 10
A7: TS-06 | B7: High | C7: Delivery Fee | D7: FR-07 | E7: Verify the 2,000 delivery fee and the 500,000 free-delivery threshold, including the boundary | F7: Boundary rule with direct money impact | G7: =COUNTIF('Test Cases'!$B:$B,A7) -> 7
A8: TS-07 | B8: High | C8: Registration | D8: FR-09 | E8: Verify account creation rules for name, email, password and duplicate accounts | F8: Gate to checkout; weak validation lets bad data in | G8: =COUNTIF('Test Cases'!$B:$B,A8) -> 12
A9: TS-08 | B9: High | C9: Login | D9: FR-10 | E9: Verify valid login works and failures show one generic error | F9: Gate to checkout; also a security expectation | G9: =COUNTIF('Test Cases'!$B:$B,A9) -> 5
A10: TS-09 | B10: High | C10: Session | D10: FR-11 | E10: Verify login state, logout, and that guests are blocked from checkout | F10: Controls who can buy and see personal data | G10: =COUNTIF('Test Cases'!$B:$B,A10) -> 5
A11: TS-10 | B11: High | C11: Order History | D11: FR-14 | E11: Verify customers see only their own orders, newest first, with complete details | F11: Privacy (data separation) and customer trust | G11: =COUNTIF('Test Cases'!$B:$B,A11) -> 6
A12: TS-11 | B12: Medium | C12: Product Catalog | D12: FR-01 | E12: Verify catalog displays all products with correct details, price format and out-of-stock handling | F12: Entry point of the shopping journey | G12: =COUNTIF('Test Cases'!$B:$B,A12) -> 4
A13: TS-12 | B13: Medium | C13: Search | D13: FR-02 | E13: Verify search is case-insensitive, supports partial names and handles no results | F13: Main way customers find products | G13: =COUNTIF('Test Cases'!$B:$B,A13) -> 8
... A19: TS-18 | B19: Low | C19: Responsive Layout | D19: NFR (Sec. 5) | E19: Verify layout works down to small mobile widths without horizontal scroll | F19: Many customers shop on phones | G19: =COUNTIF('Test Cases'!$B:$B,A19) -> 3
F20: Total test cases | G20: =SUM(G2:G19) -> 117

Sheet Test Cases
A1: Test Case ID | B1: Scenario ID | C1: Module | D1: PRD Ref | E1: Priority | F1: Test Case Title | G1: Type | H1: Preconditions | I1: Test Steps | J1: Test Data | K1: Expected Result | L1: Actual Result | M1: Status | N1: Bug ID | O1: Tested By | P1: Date Tested | Q1: Remarks
A2: TC-001 | B2: TS-01 | C2: Checkout | D2: FR-12 | E2: Critical | F2: Place order with all valid details | G2: Positive | H2: App open in a fresh browser session (localStorage cleared). Test account already registered. | I2: 1. Log in with the test account 2. Add Tecno Spark 20 to the cart 3. Open Cart and click 'Go to checkout' 4. Enter valid recipient, phone, address 5. Select payment method Card 6. Click 'Place order' | J2: Test account: Test User / testuser1@example.com / Passw0rd123 | Recipient: Ade Bello | Phone: 08012345678 | Address: 12 Unity Road, Ilorin | Payment: Card | K2: Order is placed and the confirmation screen is shown with an order number. | L2: Order is placed and the confirmation screen is shown with an order number. | M2: Pass | O2: Olayemi | P2: 28/09/2026
A3: TC-002 | B3: TS-01 | C3: Checkout | D3: FR-12 | E3: Critical | F3: Submit with all checkout fields empty | G3: Negative | H3: App open in a fresh browser session (localStorage cleared). Logged in with items in cart. | I3: 1. Log in with the test account 2. Add Tecno Spark 20 to the cart 3. Open Cart and click 'Go to checkout' 4. Leave every field empty 5. Click 'Place order' | J3: All fields empty | K3: Order is not placed. A visible, specific error message is shown. | L3: Order is not placed. A visible, specific error message is shown. | M3: Pass | O3: Olayemi | P3: 28/09/2026
A4: TC-003 | B4: TS-01 | C4: Checkout | D4: FR-12 | E4: Critical | F4: Recipient name left empty | G4: Negative | H4: App open in a fresh browser session (localStorage cleared). Logged in with items in cart. | I4: 1. Log in with the test account 2. Add Tecno Spark 20 to the cart 3. Open Cart and click 'Go to checkout' 4. Leave Recipient name empty; fill other fields validly 5. Click 'Place order' | J4: Recipient: (empty) | Phone: 08012345678 | Address: 12 Unity Road, Ilorin | Payment: Card | K4: Order is not placed. Error tells the customer to enter the recipient name. | L4: Order is not placed. Error tells the customer to enter the recipient name. | M4: Pass | O4: Olayemi | P4: 28/09/2026
A5: TC-004 | B5: TS-01 | C5: Checkout | D5: FR-12 | E5: Critical | F5: Phone number left empty | G5: Negative | H5: App open in a fresh browser session (localStorage cleared). Logged in with items in cart. | I5: 1. Log in with the test account 2. Add Tecno Spark 20 to the cart 3. Open Cart and click 'Go to checkout' 4. Leave Phone empty; fill other fields validly 5. Click 'Place order' | J5: Phone: (empty) | K5: Order is not placed. Error tells the customer to enter a phone number. | L5: Order is not placed. Error tells the customer to enter a phone number. | M5: Pass | O5: Olayemi | P5: 28/09/2026
A6: TC-005 | B6: TS-01 | C6: Checkout | D6: FR-12 | E6: Critical | F6: Phone with 10 digits (one below required length) | G6: Boundary | H6: App open in a fresh browser session (localStorage cleared). Logged in with items in cart. | I6: 1. Log in with the test account 2. Add Tecno Spark 20 to the cart 3. Open Cart and click 'Go to checkout' 4. Enter a 10-digit phone number; fill other fields validly 5. Click 'Place order' | J6: Phone: 0801234567 | K6: Order is not placed. Error states the phone must be exactly 11 digits. | L6: Order is not placed. Error states the phone must be exactly 11 digits. | M6: Pass | O6: Olayemi | P6: 28/09/2026
A7: TC-006 | B7: TS-01 | C7: Checkout | D7: FR-12 | E7: Critical | F7: Phone with exactly 11 digits | G7: Boundary | H7: App open in a fresh browser session (localStorage cleared). Logged in with items in cart. | I7: 1. Log in with the test account 2. Add Tecno Spark 20 to the cart 3. Open Cart and click 'Go to checkout' 4. Enter an 11-digit phone number; fill other fields validly 5. Click 'Place order' | J7: Phone: 08012345678 | K7: Phone is accepted and the order is placed. | L7: Phone is accepted and the order is placed. | M7: Pass | O7: Olayemi | P7: 28/09/2026
A8: TC-007 | B8: TS-01 | C8: Checkout | D8: FR-12 | E8: Critical | F8: Phone with 12 digits (one above required length) | G8: Boundary | H8: App open in a fresh browser session (localStorage cleared). Logged in with items in cart. | I8: 1. Log in with the test account 2. Add Tecno Spark 20 to the cart 3. Open Cart and click 'Go to checkout' 4. Enter a 12-digit phone number; fill other fields validly 5. Click 'Place order' | J8: Phone: 080123456789 | K8: Order is not placed. Error states the phone must be exactly 11 digits. | L8: Order is placed,more than 11 didgit phone number is accepted no error is stated | M8: Fail | N8: BUG-001 | O8: Olayemi | P8: 28/09/2026
A9: TC-008 | B9: TS-01 | C9: Checkout | D9: FR-12 | E9: Critical | F9: Phone containing letters (11 characters) | G9: Negative | H9: App open in a fresh browser session (localStorage cleared). Logged in with items in cart. | I9: 1. Log in with the test account 2. Add Tecno Spark 20 to the cart 3. Open Cart and click 'Go to checkout' 4. Enter an 11-character phone containing letters; fill other fields validly 5. Click 'Place order' | J9: Phone: 0801234abcd | K9: Order is not placed. Letters are rejected; error says digits only. | L9: Order is placed, letters are accepted,no error is stated | M9: Fail | N9: BUG-002 | O9: Olayemi | P9: 28/09/2026
A10: TC-009 | B10: TS-01 | C10: Checkout | D10: FR-12 | E10: Critical | F10: Phone containing symbols (11 characters) | G10: Negative | H10: App open in a fresh browser session (localStorage cleared). Logged in with items in cart. | I10: 1. Log in with the test account 2. Add Tecno Spark 20 to the cart 3. Open Cart and click 'Go to checkout' 4. Enter an 11-character phone containing a + and symbols; fill other fields validly 5. Click 'Place order' | J10: Phone: +2348012345 | K10: Order is not placed. Symbols are rejected; error says digits only. | L10: Order is placed, symbols are accepted , no error is stated | M10: Fail | N10: BUG-003 | O10: Olayemi | P10: 28/09/2026
A11: TC-010 | B11: TS-01 | C11: Checkout | D11: FR-12 | E11: Critical | F11: Delivery address left empty | G11: Negative | H11: App open in a fresh browser session (localStorage cleared). Logged in with items in cart. | I11: 1. Log in with the test account 2. Add Tecno Spark 20 to the cart 3. Open Cart and click 'Go to checkout' 4. Leave Address empty; fill other fields validly 5. Click 'Place order' | J11: Address: (empty) | K11: Order is not placed. Error tells the customer to enter a delivery address. | L11: Order is not placed. Error tells the customer to enter a delivery address. | M11: Pass | O11: Olayemi | P11: 28/09/2026
A12: TC-011 | B12: TS-01 | C12: Checkout | D12: FR-12 | E12: Critical | F12: Delivery address with spaces only | G12: Negative | H12: App open in a fresh browser session (localStorage cleared). Logged in with items in cart. | I12: 1. Log in with the test account 2. Add Tecno Spark 20 to the cart 3. Open Cart and click 'Go to checkout' 4. Enter only spaces in Address; fill other fields validly 5. Click 'Place order' | J12: Address: 5 spaces | K12: Order is not placed. Whitespace-only address is rejected. | L12: Order is not placed. Whitespace-only address is rejected. | M12: Pass | O12: Olayemi | P12: 28/09/2026
A13: TC-012 | B13: TS-01 | C13: Checkout | D13: FR-12 | E13: Critical | F13: Delivery address below the minimum length | G13: Negative | H13: App open in a fresh browser session (localStorage cleared). Logged in with items in cart. | I13: 1. Log in with the test account 2. Add Tecno Spark 20 to the cart 3. Open Cart and click 'Go to checkout' 4. Enter a very short address; fill other fields validly 5. Click 'Place order' | J13: Address: abc | K13: Order is not placed. Error asks for a full delivery address. | L13: Order is not placed. Error asks for a full delivery address. | M13: Pass | O13: Olayemi | P13: 29/09/2026
A14: TC-013 | B14: TS-01 | C14: Checkout | D14: FR-12 | E14: Critical | F14: No payment method selected | G14: Negative | H14: App open in a fresh browser session (localStorage cleared). Logged in with items in cart. | I14: 1. Log in with the test account 2. Add Tecno Spark 20 to the cart 3. Open Cart and click 'Go to checkout' 4. Fill all fields validly 5. Leave Payment method on 'Select' 6. Click 'Place order' | J14: Payment: (not selected) | K14: Order is not placed. Error tells the customer to select a payment method. | L14: Order is not placed. Error tells the customer to select a payment method. | M14: Pass | O14: Olayemi | P14: 29/09/2026
A15: TC-014 | B15: TS-01 | C15: Checkout | D15: FR-12 | E15: Critical | F15: Order can be placed with each payment method | G15: Positive | H15: App open in a fresh browser session (localStorage cleared). Logged in. | I15: 1. Log in with the test account 2. Add an item, go to checkout, fill valid details, choose Card, place order 3. Repeat with Bank transfer 4. Repeat with Pay on delivery | J15: Recipient: Ade Bello | Phone: 08012345678 | Address: 12 Unity Road, Ilorin | Payment: each of: Card, Bank transfer, Pay on delivery | K15: All three methods result in a placed order. Order history shows the chosen method for each. | L15: All three methods result in a placed order. Order history shows the chosen method for each. | M15: Pass | O15: Olayemi | P15: 29/09/2026
A16: TC-015 | B16: TS-01 | C16: Checkout | D16: FR-12 | E16: Critical | F16: Total at checkout equals cart total | G16: Positive | H16: App open in a fresh browser session (localStorage cleared). Logged in. | I16: 1. Log in with the test account 2. Add Tecno Spark 20 x1 and Anker 20W Charger x2 3. Note the cart Total 4. Click 'Go to checkout' and note the amount to pay | J16: Items: Tecno Spark 20 x1, Anker 20W Charger x2 | K16: Amount to pay at checkout equals the cart Total exactly. | L16: Amount to pay at checkout equals the cart Total exactly. | M16: Pass | O16: Olayemi | P16: 29/09/2026
A17: TC-016 | B17: TS-02 | C17: Order Confirmation | D17: FR-13 | E17: Critical | F17: Confirmation shows order number and total paid | G17: Positive | H17: App open in a fresh browser session (localStorage cleared). Logged in with items in cart. | I17: 1. Log in with the test account 2. Add Tecno Spark 20 to the cart 3. Open Cart and click 'Go to checkout' 4. Enter valid details and place the order | J17: Recipient: Ade Bello | Phone: 08012345678 | Address: 12 Unity Road, Ilorin | Payment: Card | K17: Confirmation shows a generated order number and the total paid. | L17: Confirmation shows a generated order number and the total paid. | M17: Pass | O17: Olayemi | P17: 29/09/2026
A18: TC-017 | B18: TS-02 | C18: Order Confirmation | D18: FR-13 | E18: Critical | F18: Cart is cleared after placing an order | G18: Positive | H18: App open in a fresh browser session (localStorage cleared). Logged in with items in cart. | I18: 1. Log in with the test account 2. Add Tecno Spark 20 to the cart 3. Open Cart and click 'Go to checkout' 4. Enter valid details and place the order 5. Check the cart count in the header 6. Open Cart | J18: Recipient: Ade Bello | Phone: 08012345678 | Address: 12 Unity Road, Ilorin | Payment: Card | K18: Cart count shows 0 and the Cart page shows the empty-cart message. | L18: Cart count shows 0 and the Cart page shows the empty-cart message. | M18: Pass | O18: Olayemi | P18: 29/09/2026
A19: TC-018 | B19: TS-02 | C19: Order Confirmation | D19: FR-13 | E19: Critical | F19: Applied coupon is cleared after placing an order | G19: Positive | H19: App open in a fresh browser session (localStorage cleared). Logged in. | I19: 1. Log in with the test account 2. Add Tecno Spark 20, apply coupon SAVE10 in Cart 3. Go to checkout and place an order with valid details 4. Add Tecno Spark 20 to the cart again and open Cart | J19: Coupon: SAVE10 | Recipient: Ade Bello | Phone: 08012345678 | Address: 12 Unity Road, Ilorin | Payment: Card | K19: The new cart shows no coupon applied and no discount. | L19: The new cart shows no coupon applied and no discount. | M19: Pass | O19: Olayemi | P19: 29/09/2026
A20: TC-019 | B20: TS-02 | C20: Order Confirmation | D20: FR-13 | E20: Critical | F20: Order numbers are unique across orders | G20: Positive | H20: App open in a fresh browser session (localStorage cleared). Logged in. | I20: 1. Log in with the test account 2. Place one order and note the order number 3. Place a second order and note the order number | J20: Recipient: Ade Bello | Phone: 08012345678 | Address: 12 Unity Road, Ilorin | Payment: Card | K20: The two order numbers are different. | L20: The two order numbers are different. | M20: Pass | O20: Olayemi | P20: 29/09/2026
A21: TC-020 | B21: TS-02 | C21: Order Confirmation | D21: FR-13 | E21: Critical | F21: Total paid on confirmation matches checkout total | G21: Positive | H21: App open in a fresh browser session (localStorage cleared). Logged in. | I21: 1. Log in with the test account 2. Add Tecno Spark 20 x1, go to checkout and note the amount to pay 3. Place the order and read the total on the confirmation screen | J21: Recipient: Ade Bello | Phone: 08012345678 | Address: 12 Unity Road, Ilorin | Payment: Card | K21: Total paid on confirmation equals the amount shown at checkout. | L21: Total paid on confirmation equals the amount shown at checkout. | M21: Pass | O21: Olayemi | P21: 29/09/2026
A22: TC-021 | B22: TS-02 | C22: Order Confirmation | D22: FR-13 | E22: Critical | F22: Double-click 'Place order' | G22: Negative | H22: App open in a fresh browser session (localStorage cleared). Logged in with items in cart. | I22: 1. Log in with the test account 2. Add Tecno Spark 20 to the cart 3. Open Cart and click 'Go to checkout' 4. Fill valid details 5. Double-click 'Place order' quickly 6. Open Orders | J22: Recipient: Ade Bello | Phone: 08012345678 | Address: 12 Unity Road, Ilorin | Payment: Card | K22: Only one order is created for the cart. | L22: Only one order is created for the cart. | M22: Pass | O22: Olayemi | P22: 29/09/2026 | Q22: Implied by FR-13 (unique order number, cart cleared). Confirm intent if the result is unclear.
A23: TC-022 | B23: TS-03 | C23: Order Total | D23: FR-08 | E23: Critical | F23: Total for a single item below the free-delivery threshold | G23: Positive | H23: App open in a fresh browser session (localStorage cleared). | I23: 1. Add Tecno Spark 20 x1 to the cart 2. Open Cart and read Subtotal, Delivery, Discount, Total | J23: Tecno Spark 20 = 145,000 | K23: Subtotal 145,000 | Delivery 2,000 | Discount 0 | Total 147,000. | L23: Subtotal 145,000 | Delivery 2,000 | Discount 0 | Total 147,000. | M23: Pass | O23: Olayemi | P23: 29/09/2026
A24: TC-023 | B24: TS-03 | C24: Order Total | D24: FR-08 | E24: Critical | F24: Total for multiple items | G24: Positive | H24: App open in a fresh browser session (localStorage cleared). | I24: 1. Add Tecno Spark 20 x1 2. Add Anker 20W Charger x2 3. Open Cart and read the totals | J24: 145,000 + (2 x 12,500) | K24: Subtotal 170,000 | Delivery 2,000 | Total 172,000. | L24: Subtotal 170,000 | Delivery 2,000 | Total 172,000. | M24: Pass | O24: Olayemi | P24: 29/09/2026
A25: TC-024 | B25: TS-03 | C25: Order Total | D25: FR-08 | E25: Critical | F25: Total with a coupon applied | G25: Positive | H25: App open in a fresh browser session (localStorage cleared). | I25: 1. Add Tecno Spark 20 x1 and Anker 20W Charger x2 2. Open Cart and apply coupon SAVE10 3. Read the totals | J25: Subtotal 170,000 | Coupon SAVE10 | K25: Discount 17,000 | Delivery 2,000 | Total 155,000. | L25: Discount 17,000 | Delivery 2,000 | Total 155,000. | M25: Pass | O25: Olayemi | P25: 29/09/2026
A26: TC-025 | B26: TS-03 | C26: Order Total | D26: FR-08 | E26: Critical | F26: Total updates when quantity changes | G26: Positive | H26: App open in a fresh browser session (localStorage cleared). | I26: 1. Add Tecno Spark 20 x1 2. Open Cart and change quantity to 3 3. Read the totals | J26: Quantity 1 to 3 | K26: Subtotal 435,000 | Delivery 2,000 | Total 437,000. | L26: Subtotal 435,000 | Delivery 2,000 | Total 437,000. | M26: Pass | O26: Olayemi | P26: 29/09/2026
A27: TC-026 | B27: TS-03 | C27: Order Total | D27: FR-08 | E27: Critical | F27: Total updates when an item is removed | G27: Positive | H27: App open in a fresh browser session (localStorage cleared). | I27: 1. Add Tecno Spark 20 x1 and Anker 20W Charger x2 2. Open Cart and remove the Anker charger 3. Read the totals | J27: Remove Anker 20W Charger | K27: Subtotal 145,000 | Delivery 2,000 | Total 147,000. | L27: Subtotal 145,000 | Delivery 2,000 | Total 147,000. | M27: Pass | O27: Olayemi | P27: 29/09/2026
A28: TC-027 | B28: TS-03 | C28: Order Total | D28: FR-08 | E28: Critical | F28: Total is identical in cart, checkout and confirmation | G28: Positive | H28: App open in a fresh browser session (localStorage cleared). Logged in. | I28: 1. Log in with the test account 2. Add Tecno Spark 20 x1 and Anker 20W Charger x2 and apply SAVE10 3. Compare Total in Cart, amount at checkout, and Total paid on confirmation | J28: Recipient: Ade Bello | Phone: 08012345678 | Address: 12 Unity Road, Ilorin | Payment: Card | K28: All three screens show the same amount. | L28: All three screens show the same amount. | M28: Pass | O28: Olayemi | P28: 29/09/2026
A29: TC-028 | B29: TS-04 | C29: Cart | D29: FR-05 | E29: Critical | F29: Add an in-stock product to the cart | G29: Positive | H29: App open in a fresh browser session (localStorage cleared). | I29: 1. Click 'Add to cart' on Tecno Spark 20 | J29: Tecno Spark 20 | K29: Product is added; header cart count is 1; a line appears in Cart. | L29: Product is added; header cart count is 1; a line appears in Cart. | M29: Pass | O29: Olayemi | P29: 29/09/2026
A30: TC-029 | B30: TS-04 | C30: Cart | D30: FR-05 | E30: Critical | F30: Add the same product twice increments quantity | G30: Positive | H30: App open in a fresh browser session (localStorage cleared). | I30: 1. Click 'Add to cart' on Tecno Spark 20 twice 2. Open Cart | J30: Tecno Spark 20 | K30: One cart line with quantity 2 (not two separate lines). | L30: One cart line with quantity 2 (not two separate lines). | M30: Pass | O30: Olayemi | P30: 29/09/2026
A31: TC-030 | B31: TS-04 | C31: Cart | D31: FR-05 | E31: Critical | F31: Add different products | G31: Positive | H31: App open in a fresh browser session (localStorage cleared). | I31: 1. Add Tecno Spark 20 2. Add JBL Flip 6 Speaker 3. Open Cart | J31: Two different products | K31: Two separate lines; header count is 2. | L31: Two separate lines; header count is 2. | M31: Pass | O31: Olayemi | P31: 29/09/2026
A32: TC-031 | B32: TS-04 | C32: Cart | D32: FR-05 | E32: Critical | F32: Quantity equal to available stock | G32: Boundary | H32: App open in a fresh browser session (localStorage cleared). | I32: 1. Add JBL Flip 6 Speaker to the cart 2. Open Cart and set quantity to 7 | J32: JBL Flip 6 stock: 7 | Quantity: 7 | K32: Quantity 7 is accepted. | L32: Quantity 7 is accepted. | M32: Pass | O32: Olayemi | P32: 29/09/2026
A33: TC-032 | B33: TS-04 | C33: Cart | D33: FR-05 | E33: Critical | F33: Quantity one above available stock | G33: Boundary | H33: App open in a fresh browser session (localStorage cleared). | I33: 1. Add JBL Flip 6 Speaker to the cart 2. Open Cart and set quantity to 8 | J33: JBL Flip 6 stock: 7 | Quantity: 8 | K33: Quantity 8 is rejected or capped at stock; a message explains why. | L33: Quantity 8 is accepted,no error message | M33: Fail | N33: BUG-004 | O33: Olayemi | P33: 29/09/2026
A34: TC-033 | B34: TS-04 | C34: Cart | D34: FR-05 | E34: Critical | F34: Add to cart repeatedly beyond available stock | G34: Negative | H34: App open in a fresh browser session (localStorage cleared). | I34: 1. Click 'Add to cart' on Lenovo ThinkPad E14 three times 2. Open Cart | J34: ThinkPad E14 stock: 2 | K34: Cart never holds more than 2; the third add is blocked with a clear message. | L34: Cart holds more than 2; the third add is not blocked and no clear message. | M34: Fail | N34: BUG-005 | O34: Olayemi | P34: 29/09/2026
A35: TC-034 | B35: TS-04 | C35: Cart | D35: FR-05 | E35: Critical | F35: Quantity set to 0 | G35: Negative | H35: App open in a fresh browser session (localStorage cleared). | I35: 1. Add Tecno Spark 20 2. Open Cart and set quantity to 0 | J35: Quantity: 0 | K35: Value is rejected. Quantity stays at 1 or more. | L35: 0 Value is not rejected. | M35: Fail | N35: BUG-006 | O35: Olayemi | P35: 29/09/2026
A36: TC-035 | B36: TS-04 | C36: Cart | D36: FR-05 | E36: Critical | F36: Quantity set to a negative number | G36: Negative | H36: App open in a fresh browser session (localStorage cleared). | I36: 1. Add Tecno Spark 20 2. Open Cart and set quantity to -1 | J36: Quantity: -1 | K36: Value is rejected. Line total and Subtotal are never negative. | L36: negative Value is accepted. Line total and Subtotal are negative. | M36: Fail | N36: BUG-007 | O36: Olayemi | P36: 29/09/2026
A37: TC-036 | B37: TS-04 | C37: Cart | D37: FR-05 | E37: Critical | F37: Quantity set to a decimal | G37: Negative | H37: App open in a fresh browser session (localStorage cleared). | I37: 1. Add Tecno Spark 20 2. Open Cart and set quantity to 1.5 | J37: Quantity: 1.5 | K37: Value is rejected; only whole numbers are accepted. | L37: Value is rejected; only whole numbers are accepted. | M37: Pass | O37: Olayemi | P37: 29/09/2026
A38: TC-037 | B38: TS-04 | C38: Cart | D38: FR-05 | E38: Critical | F38: Quantity field cleared or non-numeric | G38: Negative | H38: App open in a fresh browser session (localStorage cleared). | I38: 1. Add Tecno Spark 20 2. Open Cart, clear the quantity field, then try typing letters | J38: Quantity: (empty) / abc | K38: Value is rejected; quantity stays a whole number of 1 or more. | L38: Value is blocked/rejected; quantity stays a whole number of 1 or more. | M38: Pass | O38: Olayemi | P38: 29/09/2026
A39: TC-038 | B39: TS-04 | C39: Cart | D39: FR-05 | E39: Critical | F39: Editing quantity updates the line total | G39: Positive | H39: App open in a fresh browser session (localStorage cleared). | I39: 1. Add Anker 20W Charger 2. Open Cart and set quantity to 4 | J39: 12,500 x 4 | K39: Line total shows 50,000. | L39: Line total shows 50,000. | M39: Pass | O39: Olayemi | P39: 29/09/2026
A40: TC-039 | B40: TS-04 | C40: Cart | D40: FR-05 | E40: Critical | F40: Remove an item from the cart | G40: Positive | H40: App open in a fresh browser session (localStorage cleared). | I40: 1. Add Tecno Spark 20 and JBL Flip 6 Speaker 2. Open Cart and click Remove on Tecno Spark 20 | J40: Remove Tecno Spark 20 | K40: Only that line is deleted; the other line and the count remain correct. | L40: Only that line is deleted; the other line and the count remain correct. | M40: Pass | O40: Olayemi | P40: 29/09/2026
A41: TC-040 | B41: TS-04 | C41: Cart | D41: FR-05 | E41: Critical | F41: Remove the last item shows the empty-cart state | G41: Positive | H41: App open in a fresh browser session (localStorage cleared). | I41: 1. Add one product 2. Open Cart and click Remove | J41: One item in cart | K41: Empty-cart message is shown with a link back to the shop. | L41: Empty-cart message is shown with a link back to the shop. | M41: Pass | O41: Olayemi | P41: 29/09/2026
A42: TC-041 | B42: TS-04 | C42: Cart | D42: FR-05 | E42: Critical | F42: Empty-cart link returns to the shop | G42: Positive | H42: App open in a fresh browser session (localStorage cleared). | I42: 1. Open Cart with no items 2. Click the link back to the shop | J42: Empty cart | K42: Shop page with the product catalog is shown. | L42: Shop page with the product catalog is shown. | M42: Pass | O42: Olayemi | P42: 29/09/2026
A43: TC-042 | B43: TS-05 | C43: Coupons | D43: FR-06 | E43: High | F43: Apply SAVE10 | G43: Positive | H43: App open in a fresh browser session (localStorage cleared). | I43: 1. Add Tecno Spark 20 2. Open Cart, enter SAVE10 and click 'Apply coupon' | J43: Subtotal 145,000 | SAVE10 | K43: Discount is 14,500 (10% of subtotal). Confirmation that the coupon is applied is shown. | L43: Discount is 14,500 (10% of subtotal). Confirmation that the coupon is applied is shown. | M43: Pass | O43: Olayemi | P43: 29/09/2026
A44: TC-043 | B44: TS-05 | C44: Coupons | D44: FR-06 | E44: High | F44: Apply WELCOME5 | G44: Positive | H44: App open in a fresh browser session (localStorage cleared). | I44: 1. Add Samsung Galaxy A54 2. Open Cart, enter WELCOME5 and click 'Apply coupon' | J44: Subtotal 310,000 | WELCOME5 | K44: Discount is 15,500 (5% of subtotal); Total 296,500. | L44: Discount is 15,500 (5% of subtotal); Total 296,500. | M44: Pass | O44: Olayemi | P44: 29/09/2026
A45: TC-044 | B45: TS-05 | C45: Coupons | D45: FR-06 | E45: High | F45: Coupon code in lowercase | G45: Positive | H45: App open in a fresh browser session (localStorage cleared). | I45: 1. Add Tecno Spark 20 2. Open Cart, enter save10 and apply | J45: Code: save10 | K45: Coupon is accepted; 10% discount applied. | L45: Coupon is accepted; 10% discount applied. | M45: Pass | O45: Olayemi | P45: 29/09/2026
A46: TC-045 | B46: TS-05 | C46: Coupons | D46: FR-06 | E46: High | F46: Coupon code in mixed case | G46: Positive | H46: App open in a fresh browser session (localStorage cleared). | I46: 1. Add Tecno Spark 20 2. Open Cart, enter Welcome5 and apply | J46: Code: Welcome5 | K46: Coupon is accepted; 5% discount applied. | L46: Coupon is accepted; 5% discount applied. | M46: Pass | O46: Olayemi | P46: 29/09/2026
A47: TC-046 | B47: TS-05 | C47: Coupons | D47: FR-06 | E47: High | F47: Invalid coupon code | G47: Negative | H47: App open in a fresh browser session (localStorage cleared). | I47: 1. Add Tecno Spark 20 2. Open Cart, enter FREE100 and apply | J47: Code: FREE100 | K47: An error is shown; no discount is applied; Total unchanged. | L47: An error is shown; Invalid coupon code, no discount is applied; Total unchanged. | M47: Pass | O47: Olayemi | P47: 29/09/2026
A48: TC-047 | B48: TS-05 | C48: Coupons | D48: FR-06 | E48: High | F48: Apply with the coupon field empty | G48: Negative | H48: App open in a fresh browser session (localStorage cleared). | I48: 1. Add Tecno Spark 20 2. Open Cart, leave the coupon field empty and click 'Apply coupon' | J48: Code: (empty) | K48: No discount is applied and the customer is told the code is invalid or missing. | L48: No discount is applied and the customer is told the code is invalid or missing. | M48: Pass | O48: Olayemi | P48: 30/09/2026 | Q48: PRD only covers invalid codes. PRD gap: exact behavior not stated. Confirm with the product owner before logging a bug.
A49: TC-048 | B49: TS-05 | C49: Coupons | D49: FR-06 | E49: High | F49: Apply the same coupon repeatedly does not stack | G49: Negative | H49: App open in a fresh browser session (localStorage cleared). | I49: 1. Add Tecno Spark 20 2. Open Cart and apply SAVE10 3. Click 'Apply coupon' again with SAVE10 two more times | J49: Subtotal 145,000 | SAVE10 x3 | K49: Discount stays 14,500 (one 10%). It never increases. | L49: Discount keep increasing,more than 10%. | M49: Fail | N49: BUG-008 | O49: Olayemi | P49: 30/09/2026
A50: TC-049 | B50: TS-05 | C50: Coupons | D50: FR-06 | E50: High | F50: A second valid coupon replaces the first | G50: Negative | H50: App open in a fresh browser session (localStorage cleared). | I50: 1. Add Tecno Spark 20 2. Apply SAVE10 3. Apply WELCOME5 | J50: SAVE10 then WELCOME5 | K50: Only WELCOME5 applies (7,250 off 145,000). Discounts are not added together. | L50: Discounts are added together. | M50: Fail | N50: BUG-009 | O50: Olayemi | P50: 30/09/2026
A51: TC-050 | B51: TS-05 | C51: Coupons | D51: FR-06 | E51: High | F51: Invalid coupon entered after a valid one | G51: Negative | H51: App open in a fresh browser session (localStorage cleared). | I51: 1. Add Tecno Spark 20 2. Apply SAVE10 3. Enter FREE100 and apply | J51: SAVE10 then FREE100 | K51: An error is shown and no extra discount is added. | L51: An error is shown and no extra discount is added. | M51: Pass | O51: Olayemi | Q51: PRD does not say whether SAVE10 stays applied. PRD gap: exact behavior not stated. Confirm with the product owner before logging a bug.
A52: TC-051 | B52: TS-05 | C52: Coupons | D52: FR-06 | E52: High | F52: Discount recalculates when the subtotal changes | G52: Positive | H52: App open in a fresh browser session (localStorage cleared). | I52: 1. Add Tecno Spark 20 and apply SAVE10 2. Change quantity to 2 3. Read the totals | J52: Subtotal 290,000 | SAVE10 | K52: Discount is 29,000 and Total is 263,000. | L52: Discount is 29,000 and Total is 263,000. | M52: Pass | O52: Olayemi | Q52: PRD says 'Total = subtotal + delivery - discount, always'; a percentage discount is expected to follow the subtotal.
A53: TC-052 | B53: TS-06 | C53: Delivery Fee | D53: FR-07 | E53: High | F53: Delivery fee on a small order | G53: Positive | H53: App open in a fresh browser session (localStorage cleared). | I53: 1. Add USB-C Cable 1m x1 2. Open Cart | J53: Subtotal 4,500 | K53: Delivery shows 2,000; Total 6,500. | L53: Delivery shows 2,000; Total 6,500. | M53: Pass | O53: Olayemi
A54: TC-053 | B54: TS-06 | C54: Delivery Fee | D54: FR-07 | E54: High | F54: Subtotal just below the threshold | G54: Boundary | H54: App open in a fresh browser session (localStorage cleared). | I54: 1. Add Anker 20W Charger and set quantity to 39 2. Add USB-C Cable 1m and set quantity to 2 3. Open Cart | J54: 39 x 12,500 + 2 x 4,500 = 496,500 | K54: Delivery shows 2,000. | L54: Delivery shows 2,000. | M54: Pass | O54: Olayemi
A55: TC-054 | B55: TS-06 | C55: Delivery Fee | D55: FR-07 | E55: High | F55: Subtotal exactly at the threshold | G55: Boundary | H55: App open in a fresh browser session (localStorage cleared). | I55: 1. Add Anker 20W Charger and set quantity to 40 2. Open Cart | J55: 40 x 12,500 = 500,000 | K55: Delivery is free; Total is 500,000. | L55: Delivery is free; Total is 500,000. | M55: Pass | O55: Olayemi
A56: TC-055 | B56: TS-06 | C56: Delivery Fee | D56: FR-07 | E56: High | F56: Subtotal just above the threshold | G56: Boundary | H56: App open in a fresh browser session (localStorage cleared). | I56: 1. Add Anker 20W Charger and set quantity to 40 2. Add USB-C Cable 1m 3. Open Cart | J56: 500,000 + 4,500 = 504,500 | K56: Delivery is free; Total is 504,500. | L56: Delivery is free; Total is 504,500. | M56: Pass | O56: Olayemi
A57: TC-056 | B57: TS-06 | C57: Delivery Fee | D57: FR-07 | E57: High | F57: Single high-value item | G57: Positive | H57: App open in a fresh browser session (localStorage cleared). | I57: 1. Add HP Pavilion 15 Laptop 2. Open Cart | J57: Subtotal 680,000 | K57: Delivery is free; Total is 680,000. | L57: Delivery is free; Total is 680,000. | M57: Pass | O57: Olayemi
A58: TC-057 | B58: TS-06 | C58: Delivery Fee | D58: FR-07 | E58: High | F58: Threshold uses subtotal before discount | G58: Boundary | H58: App open in a fresh browser session (localStorage cleared). | I58: 1. Add iPhone 13 128GB 2. Open Cart and apply SAVE10 | J58: Subtotal 520,000 | SAVE10 | K58: Delivery is free (subtotal is over 500,000). Discount 52,000; Total 468,000. | L58: Delivery is free (subtotal is over 500,000). Discount 52,000; Total 468,000. | M58: Pass | O58: Olayemi | Q58: PRD says free delivery is based on 'cart subtotal'. Confirm intent if unclear.
A59: TC-058 | B59: TS-06 | C59: Delivery Fee | D59: FR-07 | E59: High | F59: Delivery fee returns when the subtotal drops below the threshold | G59: Boundary | H59: App open in a fresh browser session (localStorage cleared). | I59: 1. Add Anker 20W Charger with quantity 40 (delivery free) 2. Change quantity to 39 | J59: 500,000 to 487,500 | K59: Delivery changes from Free to 2,000 and Total updates. | L59: Delivery changes from Free to 2,000 and Total updates. | M59: Pass | O59: Olayemi
A60: TC-059 | B60: TS-07 | C60: Registration | D60: FR-09 | E60: High | F60: Register with valid details | G60: Positive | H60: App open in a fresh browser session (localStorage cleared). | I60: 1. Open the Log in page and select the 'Register' tab 2. Enter valid name, email and password 3. Click 'Create account' | J60: Test account: Test User / testuser1@example.com / Passw0rd123 | K60: Account is created and the customer is logged in automatically. Header shows 'Log out (name)'. | L60: Account is created and the customer is logged in automatically. Header shows 'Log out (name)'. | M60: Pass | O60: Olayemi
A61: TC-060 | B61: TS-07 | C61: Registration | D61: FR-09 | E61: High | F61: Full name left empty | G61: Negative | H61: App open in a fresh browser session (localStorage cleared). | I61: 1. Open the Log in page and select the 'Register' tab 2. Leave name empty; fill email and password validly 3. Click 'Create account' | J61: Name: (empty) | K61: Account is not created. Error asks for the full name. | L61: Account is not created. Error asks for the full name. | M61: Pass | O61: Olayemi
A62: TC-061 | B62: TS-07 | C62: Registration | D62: FR-09 | E62: High | F62: Email left empty | G62: Negative | H62: App open in a fresh browser session (localStorage cleared). | I62: 1. Open the Log in page and select the 'Register' tab 2. Fill name and password; leave email empty 3. Click 'Create account' | J62: Email: (empty) | K62: Account is not created. Error asks for a valid email. | L62: Account is not created. Error asks for a valid email. | M62: Pass | O62: Olayemi
A63: TC-062 | B63: TS-07 | C63: Registration | D63: FR-09 | E63: High | F63: Email without an @ symbol | G63: Negative | H63: App open in a fresh browser session (localStorage cleared). | I63: 1. Open the Log in page and select the 'Register' tab 2. Enter an email without @ 3. Click 'Create account' | J63: Email: testuser1.example.com | K63: Account is not created. Error asks for a valid email. | L63: Account is not created. Error asks for a valid email. | M63: Pass | O63: Olayemi
A64: TC-063 | B64: TS-07 | C64: Registration | D64: FR-09 | E64: High | F64: Email with no dot in the domain | G64: Negative | H64: App open in a fresh browser session (localStorage cleared). | I64: 1. Open the Log in page and select the 'Register' tab 2. Enter an email whose domain has no dot 3. Click 'Create account' | J64: Email: a@b | K64: Account is not created; the PRD says a@b is not valid. | L64: Account is created and the customer is logged in automatically. Header shows 'Log out (name)'. | M64: Fail | N64: BUG-010 | O64: Olayemi
A65: TC-064 | B65: TS-07 | C65: Registration | D65: FR-09 | E65: High | F65: Email missing the part before @ | G65: Negative | H65: App open in a fresh browser session (localStorage cleared). | I65: 1. Open the Log in page and select the 'Register' tab 2. Enter an email starting with @ 3. Click 'Create account' | J65: Email: @example.com | K65: Account is not created. Error asks for a valid email. | L65: Account is created and the customer is logged in automatically. Header shows 'Log out (name)'. | M65: Fail | N65: BUG-011 | O65: Olayemi | Q65: Implied by 'valid email'. Confirm if unclear.
A66: TC-065 | B66: TS-07 | C66: Registration | D66: FR-09 | E66: High | F66: Email containing a space | G66: Negative | H66: App open in a fresh browser session (localStorage cleared). | I66: 1. Open the Log in page and select the 'Register' tab 2. Enter an email with a space inside 3. Click 'Create account' | J66: Email: test user@example.com | K66: Account is not created. Error asks for a valid email. | L66: Account is created and the customer is logged in automatically. Header shows 'Log out (name)'. | M66: Fail | N66: BUG-012 | O66: Olayemi | Q66: Implied by 'valid email'. Confirm if unclear.
A67: TC-066 | B67: TS-07 | C67: Registration | D67: FR-09 | E67: High | F67: Password with 7 characters | G67: Boundary | H67: App open in a fresh browser session (localStorage cleared). | I67: 1. Open the Log in page and select the 'Register' tab 2. Enter a 7-character password 3. Click 'Create account' | J67: Password: Pass123 | K67: Account is not created. Error states the 8-character minimum. | L67: Account is not created. Error states the 8-character minimum. | M67: Pass | O67: Olayemi
A68: TC-067 | B68: TS-07 | C68: Registration | D68: FR-09 | E68: High | F68: Password with exactly 8 characters | G68: Boundary | H68: App open in a fresh browser session (localStorage cleared). | I68: 1. Open the Log in page and select the 'Register' tab 2. Enter an 8-character password 3. Click 'Create account' | J68: Password: Pass1234 | K68: Account is created successfully. | L68: Account is created successfully. | M68: Pass | O68: Olayemi
A69: TC-068 | B69: TS-07 | C69: Registration | D69: FR-09 | E69: High | F69: Password left empty | G69: Negative | H69: App open in a fresh browser session (localStorage cleared). | I69: 1. Open the Log in page and select the 'Register' tab 2. Fill name and email; leave password empty 3. Click 'Create account' | J69: Password: (empty) | K69: Account is not created. Error states the password requirement. | L69: Account is not created. Error states the password requirement. | M69: Pass | O69: Olayemi
A70: TC-069 | B70: TS-07 | C70: Registration | D70: FR-09 | E70: High | F70: Register with an email that already exists | G70: Negative | H70: App open in a fresh browser session (localStorage cleared). testuser1@example.com already registered. | I70: 1. Open the Log in page and select the 'Register' tab 2. Enter name, the existing email and a valid password 3. Click 'Create account' | J70: Email: testuser1@example.com | K70: Account is not created. Error says the email is already registered. | L70: Account is not created. Error says the email is already registered. | M70: Pass | O70: Olayemi
A71: TC-070 | B71: TS-07 | C71: Registration | D71: FR-09 | E71: High | F71: Register with an existing email in different letter case | G71: Negative | H71: App open in a fresh browser session (localStorage cleared). testuser1@example.com already registered. | I71: 1. Open the Log in page and select the 'Register' tab 2. Enter TESTUSER1@EXAMPLE.COM with valid name and password 3. Click 'Create account' | J71: Email: TESTUSER1@EXAMPLE.COM | K71: Account is not created; treated as the same email that already exists. | L71: Account is not created; treated as the same email that already exists. | M71: Pass | O71: Olayemi | Q71: PRD does not mention email case. PRD gap: exact behavior not stated. Confirm with the product owner before logging a bug.
A72: TC-071 | B72: TS-08 | C72: Login | D72: FR-10 | E72: High | F72: Login with valid credentials | G72: Positive | H72: App open in a fresh browser session (localStorage cleared). Test account registered and logged out. | I72: 1. Open the Log in page 2. Enter the registered email and password 3. Click 'Log in' | J72: Test account: Test User / testuser1@example.com / Passw0rd123 | K72: Customer is logged in; header shows 'Log out (name)'. | L72: Login fails with the generic message 'Email or password is incorrect'. | M72: Fail | N72: BUG-013 | O72: Olayemi
A73: TC-072 | B73: TS-08 | C73: Login | D73: FR-10 | E73: High | F73: Login with a wrong password | G73: Negative | H73: App open in a fresh browser session (localStorage cleared). Test account registered. | I73: 1. Open the Log in page 2. Enter the registered email and a wrong password 3. Click 'Log in' | J73: Email: testuser1@example.com | Password: WrongPass1 | K73: Login fails with the generic message 'Email or password is incorrect'. | L73: Login fails with the generic message 'Email or password is incorrect'. | M73: Pass | O73: Olayemi
A74: TC-073 | B74: TS-08 | C74: Login | D74: FR-10 | E74: High | F74: Login with an unregistered email | G74: Negative | H74: App open in a fresh browser session (localStorage cleared). | I74: 1. Open the Log in page 2. Enter an unregistered email and any password 3. Click 'Log in' | J74: Email: nobody@example.com | Password: Passw0rd123 | K74: Login fails with the same generic message. | L74: Login fails with the same generic message. | M74: Pass | O74: Olayemi
A75: TC-074 | B75: TS-08 | C75: Login | D75: FR-10 | E75: High | F75: Error message does not reveal which field was wrong | G75: Negative | H75: App open in a fresh browser session (localStorage cleared). Test account registered. | I75: 1. Open the Log in page 2. Log in with a wrong password and note the message 3. Log in with an unregistered email and note the message 4. Compare the two messages | J75: See the two cases above | K75: Both messages are identical and do not say whether the email or the password was wrong. | L75: Both messages are identical and do not say whether the email or the password was wrong. | M75: Pass | O75: Olayemi
A76: TC-075 | B76: TS-08 | C76: Login | D76: FR-10 | E76: High | F76: Login with both fields empty | G76: Negative | H76: App open in a fresh browser session (localStorage cleared). | I76: 1. Open the Log in page 2. Leave email and password empty 3. Click 'Log in' | J76: Both empty | K76: Login fails with a visible error message. | L76: =IFERROR(__xludf.DUMMYFUNCTION("AI(""Fill an appropriate value for this cell based on the table context"")"),"Login fails with a visible error message.") -> Login fails with a visible error message. | M76: Pass | O76: Olayemi
A77: TC-076 | B77: TS-09 | C77: Session | D77: FR-11 | E77: High | F77: Name appears in header after login | G77: Positive | H77: App open in a fresh browser session (localStorage cleared). Test account registered. | I77: 1. Log in with the test account | J77: Test account: Test User / testuser1@example.com / Passw0rd123 | K77: Header replaces 'Log in' with 'Log out (name)'. | L77: Login fails with the generic message 'Email or password is incorrect'. | M77: Fail | N77: BUG-014 | O77: Olayemi
A78: TC-077 | B78: TS-09 | C78: Session | D78: FR-11 | E78: High | F78: Logout ends the session | G78: Positive | H78: App open in a fresh browser session (localStorage cleared). Logged in. | I78: 1. Click 'Log out' in the header | J78: Test account: Test User / testuser1@example.com / Passw0rd123 | K78: Session ends, the shop is shown, and the header shows 'Log in' again. | L78: Session ends, the shop is shown, and the header shows 'Log in' again. | M78: Pass | O78: Olayemi
A79: TC-078 | B79: TS-09 | C79: Session | D79: FR-11 | E79: High | F79: Guest cannot check out | G79: Negative | H79: App open in a fresh browser session (localStorage cleared). | I79: 1. While logged out, add Tecno Spark 20 2. Open Cart and click 'Go to checkout' | J79: Logged out | K79: Customer is sent to the login page (with a message) and cannot reach the checkout form. | L79: Customer is sent to the login page (with a message) and cannot reach the checkout form. | M79: Pass | O79: Olayemi
A80: TC-079 | B80: TS-09 | C80: Session | D80: FR-11 | E80: High | F80: Return to checkout after logging in from the checkout redirect | G80: Positive | H80: App open in a fresh browser session (localStorage cleared). Test account registered; logged out. | I80: 1. Add an item and click 'Go to checkout' while logged out 2. Log in when redirected | J80: Test account: Test User / testuser1@example.com / Passw0rd123 | K80: After login, the customer returns to checkout or is told to retry, and the cart is still intact. | L80: Login fails with the generic message 'Email or password is incorrect'. | M80: Fail | N80: BUG-015 | O80: Olayemi
A81: TC-080 | B81: TS-09 | C81: Session | D81: FR-11 | E81: High | F81: Checkout is blocked again after logging out | G81: Negative | H81: App open in a fresh browser session (localStorage cleared). Logged in with items in cart. | I81: 1. Log out 2. Open Cart and click 'Go to checkout' | J81: Logged out with items in cart | K81: Checkout is blocked and the login page is shown. | L81: Checkout is blocked and the login page is shown. | M81: Pass | O81: Olayemi | P81: =IFERROR(__xludf.DUMMYFUNCTION("AI(""Fill an appropriate value for this cell based on the table context"")"),"")
A82: TC-081 | B82: TS-10 | C82: Order History | D82: FR-14 | E82: High | F82: Order shows all required details | G82: Positive | H82: App open in a fresh browser session (localStorage cleared). Logged in. | I82: 1. Place an order with Tecno Spark 20 x1 using Card 2. Open Orders | J82: Recipient: Ade Bello | Phone: 08012345678 | Address: 12 Unity Road, Ilorin | Payment: Card | K82: The order shows order number, date, payment method, status, item list and total. | L82: The order shows order number, date, payment method, status, item list and total. | M82: Pass | O82: Olayemi
A83: TC-082 | B83: TS-10 | C83: Order History | D83: FR-14 | E83: High | F83: Orders are listed most recent first | G83: Positive | H83: App open in a fresh browser session (localStorage cleared). Logged in. | I83: 1. Place a first order 2. Place a second order 3. Open Orders | J83: Recipient: Ade Bello | Phone: 08012345678 | Address: 12 Unity Road, Ilorin | Payment: Card | K83: The second (newest) order is listed above the first. | L83: The second (newest) order is listed above the first. | M83: Pass | O83: Olayemi
A84: TC-083 | B84: TS-10 | C84: Order History | D84: FR-14 | E84: High | F84: Customer sees only their own orders | G84: Negative | H84: App open in a fresh browser session (localStorage cleared). Two registered accounts (A and B). | I84: 1. Log in as account A and place an order 2. Log out and log in as account B 3. Open Orders | J84: Account A and Account B | K84: Account B does not see account A's order. | L84: Login fails with the generic message 'Email or password is incorrect'. | M84: Fail | N84: BUG-016 | O84: Olayemi
A85: TC-084 | B85: TS-10 | C85: Order History | D85: FR-14 | E85: High | F85: Customer with no orders | G85: Positive | H85: App open in a fresh browser session (localStorage cleared). Logged in with a new account. | I85: 1. Log in with an account that has never ordered 2. Open Orders | J85: New account | K85: A clear 'no orders yet' message is shown, not a blank page. | L85: A clear 'no orders yet' message is shown, not a blank page. | M85: Pass | O85: Olayemi
A86: TC-085 | B86: TS-10 | C86: Order History | D86: FR-14 | E86: High | F86: Guest opens the Orders page | G86: Negative | H86: App open in a fresh browser session (localStorage cleared). | I86: 1. While logged out, open Orders | J86: Logged out | K86: Customer is prompted to log in; no empty or broken page. | L86: Customer is prompted to log in; no empty or broken page. | M86: Pass | O86: Olayemi
A87: TC-086 | B87: TS-10 | C87: Order History | D87: FR-14 | E87: High | F87: Order details match what was placed | G87: Positive | H87: App open in a fresh browser session (localStorage cleared). Logged in. | I87: 1. Add Tecno Spark 20 x2 and apply SAVE10 2. Place the order 3. Open Orders and compare with what was ordered | J87: Tecno Spark 20 x2 | SAVE10 | K87: Items, quantities and total in the order match the order placed. | L87: Items, quantities and total in the order match the order placed. | M87: Pass | O87: Olayemi
A88: TC-087 | B88: TS-11 | C88: Product Catalog | D88: FR-01 | E88: Medium | F88: Catalog shows all products and their details | G88: Positive | H88: App open in a fresh browser session (localStorage cleared). | I88: 1. Open the shop page 2. Review every product card | J88: 12 products | K88: 12 products shown, each with name, category, price, stock level and thumbnail. | L88: 12 products shown, each with name, category, price, stock level and thumbnail. | M88: Pass | O88: Olayemi
A89: TC-088 | B89: TS-11 | C89: Product Catalog | D89: FR-01 | E89: Medium | F89: Prices are formatted in Naira with separators | G89: Positive | H89: App open in a fresh browser session (localStorage cleared). | I89: 1. Open the shop page 2. Read the price of iPhone 13 128GB and USB-C Cable 1m | J89: iPhone 13: 520,000 | USB-C Cable: 4,500 | K89: Prices display as ₦520,000 and ₦4,500. | L89: Prices display as ₦520,000 and ₦4,500. | M89: Pass | O89: Olayemi
A90: TC-089 | B90: TS-11 | C90: Product Catalog | D90: FR-01 | E90: Medium | F90: Out-of-stock product is labeled and disabled | G90: Positive | H90: App open in a fresh browser session (localStorage cleared). | I90: 1. Find Apple Watch SE on the shop page | J90: Apple Watch SE (stock 0) | K90: Labeled 'Out of stock'; 'Add to cart' is disabled. | L90: Labeled 'Out of stock'; 'Add to cart' is disabled. | M90: Pass | O90: Olayemi
A91: TC-090 | B91: TS-11 | C91: Product Catalog | D91: FR-01 | E91: Medium | F91: Out-of-stock product cannot be added by any route | G91: Negative | H91: App open in a fresh browser session (localStorage cleared). | I91: 1. Try clicking Add to cart on Apple Watch SE 2. Try reaching the button with the keyboard (Tab + Enter) 3. Open Cart | J91: Apple Watch SE (stock 0) | K91: Item is never added to the cart by mouse or keyboard. | L91: Item is never added to the cart by mouse or keyboard. | M91: Pass | O91: Olayemi
A92: TC-091 | B92: TS-12 | C92: Search | D92: FR-02 | E92: Medium | F92: Search by exact product name | G92: Positive | H92: App open in a fresh browser session (localStorage cleared). | I92: 1. Type the full name in the search box | J92: Tecno Spark 20 | K92: Only Tecno Spark 20 is shown. | L92: Only Tecno Spark 20 is shown. | M92: Pass | O92: Olayemi
A93: TC-092 | B93: TS-12 | C93: Search | D93: FR-02 | E93: Medium | F93: Search by partial name | G93: Positive | H93: App open in a fresh browser session (localStorage cleared). | I93: 1. Type part of a name in the search box | J93: phone | K93: Products whose name contains 'phone' are shown (iPhone 13 128GB). | L93: error message "No products match "phone". Try a different search." | M93: Fail | N93: BUG-018 | O93: Olayemi
A94: TC-093 | B94: TS-12 | C94: Search | D94: FR-02 | E94: Medium | F94: Search in lowercase | G94: Positive | H94: App open in a fresh browser session (localStorage cleared). | I94: 1. Type the name in all lowercase | J94: iphone | K94: iPhone 13 128GB is shown (search is case-insensitive). | L94: error message "No products match "iphone". Try a different search." | M94: Fail | N94: BUG-019 | O94: Olayemi
A95: TC-094 | B95: TS-12 | C95: Search | D95: FR-02 | E95: Medium | F95: Search in uppercase | G95: Positive | H95: App open in a fresh browser session (localStorage cleared). | I95: 1. Type the name in all uppercase | J95: AIRPODS | K95: AirPods Pro is shown. | L95: error message "No products match "AIRPODS". Try a different search." | M95: Fail | N95: BUG-020 | O95: Olayemi
A96: TC-095 | B96: TS-12 | C96: Search | D96: FR-02 | E96: Medium | F96: Search with no matching product | G96: Negative | H96: App open in a fresh browser session (localStorage cleared). | I96: 1. Type a term that matches nothing | J96: xyz123 | K96: A 'no results' message that includes the search term is shown. | L96: No products match "xyz123". Try a different search. | M96: Pass | O96: Olayemi
A97: TC-096 | B97: TS-12 | C97: Search | D97: FR-02 | E97: Medium | F97: Clearing the search shows all products | G97: Positive | H97: App open in a fresh browser session (localStorage cleared). | I97: 1. Type a search term 2. Clear the search box | J97: Search: tecno then cleared | K97: All 12 products are shown again. | L97: All 12 products are shown again. | M97: Pass | O97: Olayemi
A98: TC-097 | B98: TS-12 | C98: Search | D98: FR-02 | E98: Medium | F98: Search combined with a category filter | G98: Positive | H98: App open in a fresh browser session (localStorage cleared). | I98: 1. Select category 'Wearables' 2. Type 'watch' in the search box 3. Change category to 'Phones' | J98: Search: watch | K98: Wearables: Apple Watch SE shown. Phones: no results message. | L98: Wearables: Apple Watch SE shown. Phones: no results message. | M98: Pass | O98: Olayemi
A99: TC-098 | B99: TS-12 | C99: Search | D99: FR-02 | E99: Medium | F99: Search with special characters | G99: Negative | H99: App open in a fresh browser session (localStorage cleared). | I99: 1. Type HTML-like text in the search box | J99: <b>test</b> | K99: No results message is shown; layout is not broken and no markup or script is executed. | L99: No results message is shown; layout is not broken and no markup or script is executed. | M99: Pass | O99: Olayemi
A100: TC-099 | B100: TS-13 | C100: Sort | D100: FR-04 | E100: Medium | F100: Sort price low to high | G100: Positive | H100: App open in a fresh browser session (localStorage cleared). | I100: 1. Select 'Price: low to high' 2. Read the prices from top to bottom | J100: 12 products | K100: Order: 4,500 | 12,500 | 22,000 | 38,000 | 95,000 | 145,000 | 185,000 | 260,000 | 310,000 | 520,000 | 680,000 | 750,000. | L100: Order: 4,500 | 12,500 | 22,000 | 38,000 | 95,000 | 145,000 | 185,000 | 260,000 | 310,000 | 520,000 | 680,000 | 750,000. | M100: Pass | O100: Olayemi
...

Sheet Bug Report
A1: Bug ID | B1: Bug Title | C1: Module | D1: PRD Ref | E1: Related Test Case ID | F1: Severity | G1: Priority | H1: Status | I1: Environment (Browser / OS / Version) | J1: Preconditions | K1: Steps to Reproduce | L1: Expected Result | M1: Actual Result | N1: Evidence (Screenshot / Video Link) | O1: Reported By | P1: Date Reported | Q1: Assigned To | R1: Retest Result | S1: Date Closed | T1: Remarks
A2: BUG-001 | B2: Checkout accepts phone numbers longer than 11 digits with no validation error | C2: Checkout | D2: FR-12 | E2: TC-008 | F2: Major | G2: High | H2: New | I2: Google Chrome Browser | J2: Logged in with items in cart | K2: Go to checkout > enter a phone number of 12 digits (e.g. 080123456789) > fill other fields validly > click "Place order | L2: Order is not placed. Error states the phone must be exactly 11 digits. | M2: A phone number longer than 11 digits is accepted with no error shown. | P2: 28/09/2026
A3: BUG-002 | B3: Checkout accepts letters in the phone number field | C3: Checkout | D3: FR-12 | E3: TC-009 | F3: Major | G3: High | H3: New | I3: Google Chrome Browser | J3: Logged in with items in cart | K3: Go to checkout > enter phone number 0801234abcd (11 characters, contains letters) > fill other fields validly > click "Place order" | L3: Order is not placed. Letters are rejected; error says digits only. | M3: Order is placed. Letters are accepted in the phone field with no error shown. | P3: 28/09/2026
A4: BUG-003 | B4: Checkout accepts symbols and more than 11 characters in the phone number | C4: Checkout | D4: FR-12 | E4: TC-010 | F4: Major | G4: High | H4: New | I4: Google Chrome Browser | J4: Logged in with items in cart | K4: Go to checkout > enter phone number +2348012345 (contains a symbol, 11 characters) > fill other fields validly > click "Place order" | L4: Symbols are rejected; error says digits only. | M4: Order is placed. Symbols are accepted, with no error shown. | P4: 28/09/2026
A5: BUG-004
A6: BUG-005
A7: BUG-006
A8: BUG-007
A9: BUG-008
A10: BUG-009
A11: BUG-010
A12: BUG-011
A13: BUG-012
A14: BUG-013
A15: BUG-014
A16: BUG-015
... A61: BUG-060

Sheet Read Me & Summary
A1: Voltcart Test Documentation
A2: Product | B2: Voltcart gadget store. Source of truth: Voltcart PRD v1.0 (FR-01 to FR-14 plus non-functional expectations).
A3: Tabs | B3: Test Scenarios (ranked by importance) > Test Cases (linked by Scenario ID) > Bug Report (blank log).
A5: Execution summary (updates live)
A6: Total test cases | B6: =COUNTA('Test Cases'!A2:A118) -> 117
A7: Not Run | B7: =COUNTIF('Test Cases'!M2:M118,"Not Run") -> 0
A8: Pass | B8: =COUNTIF('Test Cases'!M2:M118,"Pass") -> 97
A9: Fail | B9: =COUNTIF('Test Cases'!M2:M118,"Fail") -> 20
A10: Blocked | B10: =COUNTIF('Test Cases'!M2:M118,"Blocked") -> 0
A11: Skipped | B11: =COUNTIF('Test Cases'!M2:M118,"Skipped") -> 0
A12: Pass rate (of executed cases) | B12: =IFERROR(B8/(B8+B9+B10),"No cases executed yet") -> 0.82905983
A13: Bugs logged | B13: =COUNTA('Bug Report'!B2:B61) -> 3
A14: Bugs still open | B14: =COUNTIFS('Bug Report'!B2:B61,"<>",'Bug Report'!H2:H61,"<>Closed",'Bug Report'!H2:H61,"<>Rejected") -> 3
A23: Severity (impact on the product)
A24: Critical | B24: Blocks a core journey or causes wrong money amounts or data loss (e.g. cannot place order, wrong total).
A25: Major | B25: Important feature works incorrectly but a workaround exists.
A26: Minor | B26: Small functional or validation issue with low business impact.
A27: Trivial | B27: Cosmetic issue (spelling, alignment, styling).
A29: Priority (urgency to fix)
A30: High | B30: Fix immediately, before release.
A31: Medium | B31: Fix in the current cycle.
A32: Low | B32: Fix when time allows.
A37: Environment tip | B37: Always record browser name and version, OS, and screen size in the Bug Report Environment column.
